merge_xlsx/cli.py
merge_xlsx-0.1.2.dist-info/LICENSE
merge_xlsx-0.1.2.dist-info/METADATA
merge_xlsx-0.1.2.dist-info/WHEEL
merge_xlsx-0.1.2.dist-info/entry_points.txt
merge_xlsx-0.1.2.dist-info/RECORD
